{
  "db5dfdaabd7969406286fd0cbc3c6c97" : {
    "statistic" : {
      "failed" : 0,
      "broken" : 0,
      "skipped" : 0,
      "passed" : 1,
      "unknown" : 0,
      "total" : 1
    },
    "items" : [ {
      "uid" : "f560cbb4a7be49ab",
      "reportUrl" : "https://dobosbrigi91.github.io/conduit/33//#testresult/f560cbb4a7be49ab",
      "status" : "passed",
      "time" : {
        "start" : 1627673189001,
        "stop" : 1627673223949,
        "duration" : 34948
      }
    } ]
  },
  "f7200f8d0a6b49f2cdc3ed62423124d8" : {
    "statistic" : {
      "failed" : 0,
      "broken" : 0,
      "skipped" : 0,
      "passed" : 1,
      "unknown" : 0,
      "total" : 1
    },
    "items" : [ {
      "uid" : "b81a6d6a0d065eaa",
      "reportUrl" : "https://dobosbrigi91.github.io/conduit/33//#testresult/b81a6d6a0d065eaa",
      "status" : "passed",
      "time" : {
        "start" : 1627673292326,
        "stop" : 1627673372882,
        "duration" : 80556
      }
    } ]
  },
  "0e9e806835091c2170ae91dd7a206068" : {
    "statistic" : {
      "failed" : 0,
      "broken" : 0,
      "skipped" : 0,
      "passed" : 1,
      "unknown" : 0,
      "total" : 1
    },
    "items" : [ {
      "uid" : "93e9b5281ccb54b7",
      "reportUrl" : "https://dobosbrigi91.github.io/conduit/33//#testresult/93e9b5281ccb54b7",
      "status" : "passed",
      "time" : {
        "start" : 1627673223953,
        "stop" : 1627673292322,
        "duration" : 68369
      }
    } ]
  }
}